esapy/__init__.py
esapy/api_esa.py
esapy/api_growi.py
esapy/entrypoint.py
esapy/helper.py
esapy/loadrc.py
esapy/processor.py
esapy-2.0.1.dist-info/entry_points.txt
esapy-2.0.1.dist-info/LICENSE
esapy-2.0.1.dist-info/WHEEL
esapy-2.0.1.dist-info/METADATA
esapy-2.0.1.dist-info/RECORD
