Metadata-Version: 2.1
Name: esapy
Version: 2.0.1
Summary: Upload jupyter notebook for your wiki. Suported wiki: esa.io and growi.
Home-page: https://github.com/KosukeMizuno/esapy
License: MIT
Author: Kosuke Mizuno
Author-email: dotmapu@gmail.com
Requires-Python: >=3.4
Classifier: License :: OSI Approved :: MIT License
Classifier: Programming Language :: Python :: 3
Classifier: Programming Language :: Python :: 3.4
Classifier: Programming Language :: Python :: 3.5
Classifier: Programming Language :: Python :: 3.6
Classifier: Programming Language :: Python :: 3.7
Classifier: Programming Language :: Python :: 3.8
Classifier: Programming Language :: Python :: 3.9
Requires-Dist: gitpython
Requires-Dist: pyyaml
Requires-Dist: requests
